tinybird_toolset-2.0.0.dist-info/RECORD
tinybird_toolset-2.0.0.dist-info/WHEEL
tinybird_toolset-2.0.0.dist-info/top_level.txt
tinybird_toolset-2.0.0.dist-info/METADATA
tinybird_toolset-2.0.0.dist-info/licenses/LICENSE
chtoolset/query.py
chtoolset/__init__.py
chtoolset/_query.cpython-312-darwin.so
