Metadata-Version: 2.4
Name: tinybird-toolset
Version: 2.0.0
Home-page: https://gitlab.com/tinybird/clickhouse-toolset
Author: Tinybird.co
Author-email: support@tinybird.co
Requires-Python: >=3.10, <3.15
License-File: LICENSE
Provides-Extra: test
Requires-Dist: pytest; extra == "test"
Requires-Dist: pytest-asyncio; extra == "test"
Requires-Dist: prettytable; extra == "test"
Dynamic: author
Dynamic: author-email
Dynamic: home-page
Dynamic: license-file
Dynamic: provides-extra
Dynamic: requires-python
